container_guts/__init__.py
container_guts/defaults.py
container_guts/logger.py
container_guts/version.py
container_guts/client/__init__.py
container_guts/client/compat.py
container_guts/client/diff.py
container_guts/client/manifest.py
container_guts/client/similar.py
container_guts/main/__init__.py
container_guts/main/client.py
container_guts/main/database.py
container_guts/main/templates.py
container_guts/main/compat/__init__.py
container_guts/main/compat/client.py
container_guts/main/compat/dockerfile.py
container_guts/main/container/__init__.py
container_guts/main/container/base.py
container_guts/main/container/decorator.py
container_guts/main/container/docker.py
container_guts/utils/__init__.py
container_guts/utils/fileio.py
container_guts/utils/terminal.py
container_guts-0.0.17.dist-info/LICENSE
container_guts-0.0.17.dist-info/METADATA
container_guts-0.0.17.dist-info/WHEEL
container_guts-0.0.17.dist-info/entry_points.txt
container_guts-0.0.17.dist-info/top_level.txt
container_guts-0.0.17.dist-info/RECORD
