Metadata-Version: 2.1
Name: container-guts
Version: 0.0.17
Summary: Easily export container guts (executables on the path).
Home-page: https://github.com/singularityhub/guts
Author: Vanessa Sochat
Author-email: vsoch@users.noreply.github.com
Maintainer: Vanessa Sochat
License: LICENSE
Keywords: docker,containers,introspection
Classifier: Intended Audience :: Science/Research
Classifier: Intended Audience :: Developers
Classifier: License :: OSI Approved :: Mozilla Public License 2.0 (MPL 2.0)
Classifier: Programming Language :: C
Classifier: Programming Language :: Python
Classifier: Topic :: Software Development
Classifier: Topic :: Scientific/Engineering
Classifier: Operating System :: Unix
Classifier: Programming Language :: Python :: 3.9
License-File: LICENSE
Provides-Extra: all
Requires-Dist: pytest >=4.6.2 ; extra == 'all'
